{"hierarchy":{"paths":[["doc:\/\/swiftsafeui.SwiftSafeUI\/documentation\/SwiftSafeUI","doc:\/\/swiftsafeui.SwiftSafeUI\/documentation\/SwiftSafeUI\/SafeScrollView","doc:\/\/swiftsafeui.SwiftSafeUI\/documentation\/SwiftSafeUI\/SafeScrollView\/View-Implementations"]]},"primaryContentSections":[{"declarations":[{"languages":["swift"],"platforms":["iOS"],"tokens":[{"kind":"attribute","text":"nonisolated"},{"text":" ","kind":"text"},{"text":"func","kind":"keyword"},{"text":" ","kind":"text"},{"kind":"identifier","text":"safeSearchable"},{"text":"<","kind":"text"},{"text":"Suggestions","kind":"genericParameter"},{"text":">(","kind":"text"},{"text":"text","kind":"externalParam"},{"kind":"text","text":": "},{"kind":"typeIdentifier","preciseIdentifier":"s:7SwiftUI7BindingV","text":"Binding"},{"text":"<","kind":"text"},{"preciseIdentifier":"s:SS","kind":"typeIdentifier","text":"String"},{"text":">, ","kind":"text"},{"kind":"externalParam","text":"placement"},{"kind":"text","text":": "},{"text":"SearchFieldPlacement","kind":"typeIdentifier","preciseIdentifier":"s:7SwiftUI20SearchFieldPlacementV"},{"kind":"text","text":" = .automatic, "},{"kind":"externalParam","text":"prompt"},{"text":": ","kind":"text"},{"kind":"typeIdentifier","text":"LocalizedStringKey","preciseIdentifier":"s:7SwiftUI18LocalizedStringKeyV"},{"text":", ","kind":"text"},{"kind":"attribute","text":"@"},{"text":"ViewBuilder","preciseIdentifier":"s:7SwiftUI11ViewBuilderV","kind":"attribute"},{"kind":"text","text":" "},{"kind":"externalParam","text":"suggestions"},{"kind":"text","text":": () -> "},{"text":"Suggestions","kind":"typeIdentifier","preciseIdentifier":"s:7SwiftUI4ViewP0a4SafeB0E14safeSearchable4text9placement6prompt11suggestionsQrAA7BindingVySSG_AA20SearchFieldPlacementVAA18LocalizedStringKeyVqd__yXEtAaBRd__lFQO11Suggestionsqd__mfp"},{"text":") -> ","kind":"text"},{"kind":"keyword","text":"some"},{"kind":"text","text":" "},{"preciseIdentifier":"s:7SwiftUI4ViewP","kind":"typeIdentifier","text":"View"},{"text":" ","kind":"text"},{"text":"where","kind":"keyword"},{"kind":"text","text":" "},{"kind":"typeIdentifier","text":"Suggestions"},{"kind":"text","text":" : "},{"text":"View","kind":"typeIdentifier","preciseIdentifier":"s:7SwiftUI4ViewP"},{"text":"\n","kind":"text"}]}],"kind":"declarations"},{"kind":"parameters","parameters":[{"name":"text","content":[{"type":"paragraph","inlineContent":[{"text":"A binding to the search text.","type":"text"}]}]},{"name":"placement","content":[{"inlineContent":[{"text":"The placement of the search field. The default value is ","type":"text"},{"code":".automatic","type":"codeVoice"},{"text":".","type":"text"}],"type":"paragraph"}]},{"name":"prompt","content":[{"inlineContent":[{"type":"text","text":"A localized string to display as a placeholder in the search field."}],"type":"paragraph"}]},{"content":[{"type":"paragraph","inlineContent":[{"type":"text","text":"A closure that returns the view used to display search suggestions."}]}],"name":"suggestions"}]},{"content":[{"anchor":"return-value","type":"heading","level":2,"text":"Return Value"},{"type":"paragraph","inlineContent":[{"type":"text","text":"A view that incorporates a searchable field with suggestions."}]}],"kind":"content"},{"kind":"content","content":[{"level":2,"type":"heading","text":"Discussion","anchor":"discussion"},{"inlineContent":[{"type":"text","text":"This method provides a search functionality with suggestions for users. It adapts based on the iOS version:"}],"type":"paragraph"},{"type":"unorderedList","items":[{"content":[{"inlineContent":[{"text":"On iOS 16 and later, it uses the new ","type":"text"},{"identifier":"https:\/\/developer.apple.com\/documentation\/swiftui\/view\/searchable(text:placement:prompt:)","type":"reference","isActive":true},{"type":"text","text":" method along with "},{"identifier":"https:\/\/developer.apple.com\/documentation\/swiftui\/view\/searchsuggestions(_:)","isActive":true,"type":"reference"},{"text":".","type":"text"}],"type":"paragraph"}]},{"content":[{"type":"paragraph","inlineContent":[{"text":"On earlier versions, it falls back to the ","type":"text"},{"isActive":true,"type":"reference","identifier":"https:\/\/developer.apple.com\/documentation\/swiftui\/view\/searchable(text:placement:prompt:suggestions:)"},{"type":"text","text":" method."}]}]}]},{"type":"aside","content":[{"inlineContent":[{"type":"text","text":"This modifier requires iOS 15 or later."}],"type":"paragraph"}],"style":"important","name":"Important"},{"content":[{"type":"paragraph","inlineContent":[{"type":"text","text":"The "},{"code":"searchable","type":"codeVoice"},{"type":"text","text":" functionality itself remains consistent across all supported iOS versions. This modifier specifically addresses the "},{"type":"codeVoice","code":"searchSuggestions"},{"text":" feature on versions prior to iOS 16.","type":"text"}]}],"style":"tip","name":"Tip","type":"aside"},{"type":"heading","text":"Example","level":2,"anchor":"Example"},{"type":"codeListing","syntax":"swift","code":["struct ContentView: View {","    @State private var searchText = \"\"","","    var body: some View {","        List {","            \/\/ List items...","        }","        .safeSearchable($searchText, prompt: \"Search items\") {","            Text(\"🍎\").searchCompletion(\"apple\")","            Text(\"🍐\").searchCompletion(\"pear\")","            Text(\"🍌\").searchCompletion(\"banana\")","        }","    }","}"]}]}],"variants":[{"traits":[{"interfaceLanguage":"swift"}],"paths":["\/documentation\/swiftsafeui\/safescrollview\/safesearchable(text:placement:prompt:suggestions:)"]}],"metadata":{"fragments":[{"text":"func","kind":"keyword"},{"kind":"text","text":" "},{"text":"safeSearchable","kind":"identifier"},{"text":"<","kind":"text"},{"text":"Suggestions","kind":"genericParameter"},{"text":">(","kind":"text"},{"text":"text","kind":"externalParam"},{"kind":"text","text":": "},{"text":"Binding","kind":"typeIdentifier","preciseIdentifier":"s:7SwiftUI7BindingV"},{"text":"<","kind":"text"},{"preciseIdentifier":"s:SS","text":"String","kind":"typeIdentifier"},{"text":">, ","kind":"text"},{"text":"placement","kind":"externalParam"},{"kind":"text","text":": "},{"kind":"typeIdentifier","preciseIdentifier":"s:7SwiftUI20SearchFieldPlacementV","text":"SearchFieldPlacement"},{"kind":"text","text":", "},{"text":"prompt","kind":"externalParam"},{"text":": ","kind":"text"},{"preciseIdentifier":"s:7SwiftUI18LocalizedStringKeyV","text":"LocalizedStringKey","kind":"typeIdentifier"},{"text":", ","kind":"text"},{"text":"suggestions","kind":"externalParam"},{"text":": () -> ","kind":"text"},{"kind":"typeIdentifier","preciseIdentifier":"s:7SwiftUI4ViewP0a4SafeB0E14safeSearchable4text9placement6prompt11suggestionsQrAA7BindingVySSG_AA20SearchFieldPlacementVAA18LocalizedStringKeyVqd__yXEtAaBRd__lFQO11Suggestionsqd__mfp","text":"Suggestions"},{"text":") -> ","kind":"text"},{"text":"some","kind":"keyword"},{"text":" ","kind":"text"},{"text":"View","kind":"typeIdentifier","preciseIdentifier":"s:7SwiftUI4ViewP"}],"extendedModule":"SwiftUICore","platforms":[{"unavailable":false,"name":"iOS","introducedAt":"15.0","deprecated":false,"beta":false},{"introducedAt":"15.0","deprecated":false,"beta":false,"unavailable":false,"name":"iPadOS"},{"unavailable":false,"name":"Mac Catalyst","beta":false,"introducedAt":"15.0","deprecated":false}],"title":"safeSearchable(text:placement:prompt:suggestions:)","symbolKind":"method","roleHeading":"Instance Method","modules":[{"name":"SwiftSafeUI","relatedModules":["SwiftUICore"]}],"externalID":"s:7SwiftUI4ViewP0a4SafeB0E14safeSearchable4text9placement6prompt11suggestionsQrAA7BindingVySSG_AA20SearchFieldPlacementVAA18LocalizedStringKeyVqd__yXEtAaBRd__lF::SYNTHESIZED::s:11SwiftSafeUI0B10ScrollViewV","role":"symbol"},"sections":[],"identifier":{"url":"doc:\/\/swiftsafeui.SwiftSafeUI\/documentation\/SwiftSafeUI\/SafeScrollView\/safeSearchable(text:placement:prompt:suggestions:)","interfaceLanguage":"swift"},"abstract":[{"text":"Adds a search field to this view with customizable suggestions and prompt, ensuring compatibility with different iOS versions.","type":"text"}],"kind":"symbol","schemaVersion":{"major":0,"minor":3,"patch":0},"references":{"doc://swiftsafeui.SwiftSafeUI/documentation/SwiftSafeUI/SafeScrollView/View-Implementations":{"type":"topic","abstract":[],"role":"collectionGroup","title":"View Implementations","url":"\/documentation\/swiftsafeui\/safescrollview\/view-implementations","identifier":"doc:\/\/swiftsafeui.SwiftSafeUI\/documentation\/SwiftSafeUI\/SafeScrollView\/View-Implementations","kind":"article"},"https://developer.apple.com/documentation/swiftui/view/searchable(text:placement:prompt:suggestions:)":{"type":"link","identifier":"https:\/\/developer.apple.com\/documentation\/swiftui\/view\/searchable(text:placement:prompt:suggestions:)","url":"https:\/\/developer.apple.com\/documentation\/swiftui\/view\/searchable(text:placement:prompt:suggestions:)","title":"searchable(text:placement:prompt:suggestions:)","titleInlineContent":[{"code":"searchable(text:placement:prompt:suggestions:)","type":"codeVoice"}]},"https://developer.apple.com/documentation/swiftui/view/searchable(text:placement:prompt:)":{"type":"link","identifier":"https:\/\/developer.apple.com\/documentation\/swiftui\/view\/searchable(text:placement:prompt:)","url":"https:\/\/developer.apple.com\/documentation\/swiftui\/view\/searchable(text:placement:prompt:)","title":"searchable(text:placement:prompt:)","titleInlineContent":[{"type":"codeVoice","code":"searchable(text:placement:prompt:)"}]},"SwiftSafeUI-Icon.png":{"type":"image","identifier":"SwiftSafeUI-Icon.png","alt":"A technology icon representing the SwiftSafeUI framework.","variants":[{"url":"\/images\/swiftsafeui.SwiftSafeUI\/SwiftSafeUI-Icon.png","traits":["1x","light"]}]},"doc://swiftsafeui.SwiftSafeUI/documentation/SwiftSafeUI/SafeScrollView/safeSearchable(text:placement:prompt:suggestions:)":{"kind":"symbol","type":"topic","abstract":[{"text":"Adds a search field to this view with customizable suggestions and prompt, ensuring compatibility with different iOS versions.","type":"text"}],"identifier":"doc:\/\/swiftsafeui.SwiftSafeUI\/documentation\/SwiftSafeUI\/SafeScrollView\/safeSearchable(text:placement:prompt:suggestions:)","url":"\/documentation\/swiftsafeui\/safescrollview\/safesearchable(text:placement:prompt:suggestions:)","role":"symbol","fragments":[{"text":"func","kind":"keyword"},{"text":" ","kind":"text"},{"kind":"identifier","text":"safeSearchable"},{"text":"<","kind":"text"},{"kind":"genericParameter","text":"Suggestions"},{"kind":"text","text":">("},{"text":"text","kind":"externalParam"},{"text":": ","kind":"text"},{"text":"Binding","kind":"typeIdentifier","preciseIdentifier":"s:7SwiftUI7BindingV"},{"kind":"text","text":"<"},{"text":"String","preciseIdentifier":"s:SS","kind":"typeIdentifier"},{"text":">, ","kind":"text"},{"kind":"externalParam","text":"placement"},{"text":": ","kind":"text"},{"kind":"typeIdentifier","preciseIdentifier":"s:7SwiftUI20SearchFieldPlacementV","text":"SearchFieldPlacement"},{"text":", ","kind":"text"},{"text":"prompt","kind":"externalParam"},{"kind":"text","text":": "},{"text":"LocalizedStringKey","preciseIdentifier":"s:7SwiftUI18LocalizedStringKeyV","kind":"typeIdentifier"},{"text":", ","kind":"text"},{"text":"suggestions","kind":"externalParam"},{"text":": () -> ","kind":"text"},{"kind":"typeIdentifier","text":"Suggestions","preciseIdentifier":"s:7SwiftUI4ViewP0a4SafeB0E14safeSearchable4text9placement6prompt11suggestionsQrAA7BindingVySSG_AA20SearchFieldPlacementVAA18LocalizedStringKeyVqd__yXEtAaBRd__lFQO11Suggestionsqd__mfp"},{"kind":"text","text":") -> "},{"text":"some","kind":"keyword"},{"text":" ","kind":"text"},{"preciseIdentifier":"s:7SwiftUI4ViewP","text":"View","kind":"typeIdentifier"}],"title":"safeSearchable(text:placement:prompt:suggestions:)"},"doc://swiftsafeui.SwiftSafeUI/documentation/SwiftSafeUI":{"title":"SwiftSafeUI","abstract":[{"type":"text","text":"Encapsulates deprecation handling logic, maintaining compatibility across iOS versions."}],"url":"\/documentation\/swiftsafeui","role":"collection","kind":"symbol","images":[{"type":"icon","identifier":"SwiftSafeUI-Icon.png"}],"type":"topic","identifier":"doc:\/\/swiftsafeui.SwiftSafeUI\/documentation\/SwiftSafeUI"},"doc://swiftsafeui.SwiftSafeUI/documentation/SwiftSafeUI/SafeScrollView":{"kind":"symbol","identifier":"doc:\/\/swiftsafeui.SwiftSafeUI\/documentation\/SwiftSafeUI\/SafeScrollView","url":"\/documentation\/swiftsafeui\/safescrollview","type":"topic","abstract":[{"type":"text","text":"A view that provides a scrollable container for its content, with support for different iOS versions."}],"fragments":[{"kind":"keyword","text":"struct"},{"kind":"text","text":" "},{"text":"SafeScrollView","kind":"identifier"}],"title":"SafeScrollView","navigatorTitle":[{"text":"SafeScrollView","kind":"identifier"}],"role":"symbol"},"https://developer.apple.com/documentation/swiftui/view/searchsuggestions(_:)":{"type":"link","identifier":"https:\/\/developer.apple.com\/documentation\/swiftui\/view\/searchsuggestions(_:)","url":"https:\/\/developer.apple.com\/documentation\/swiftui\/view\/searchsuggestions(_:)","title":"searchSuggestions(_:)","titleInlineContent":[{"type":"codeVoice","code":"searchSuggestions(_:)"}]}}}